HISTORY.txt
LICENSE.txt
MANIFEST.in
NOTICE.txt
README.md
requirements.txt
setup.py
dataiku_scoring.egg-info/PKG-INFO
dataiku_scoring.egg-info/SOURCES.txt
dataiku_scoring.egg-info/dependency_links.txt
dataiku_scoring.egg-info/requires.txt
dataiku_scoring.egg-info/top_level.txt
dataikuscoring/__init__.py
dataikuscoring/load.py
dataikuscoring/algorithms/__init__.py
dataikuscoring/algorithms/common.py
dataikuscoring/algorithms/decision_tree_model.py
dataikuscoring/algorithms/forest_classifier.py
dataikuscoring/algorithms/forest_regressor.py
dataikuscoring/algorithms/generic_mlp.py
dataikuscoring/algorithms/gradient_boosting_classifier.py
dataikuscoring/algorithms/gradient_boosting_regressor.py
dataikuscoring/algorithms/linear_regression.py
dataikuscoring/algorithms/logistic.py
dataikuscoring/algorithms/mlp_classifier.py
dataikuscoring/algorithms/mlp_regressor.py
dataikuscoring/mlflow/__init__.py
dataikuscoring/mlflow/classification.py
dataikuscoring/mlflow/common.py
dataikuscoring/mlflow/dss_flavor.py
dataikuscoring/mlflow/regression.py
dataikuscoring/models/__init__.py
dataikuscoring/models/binary.py
dataikuscoring/models/common.py
dataikuscoring/models/mlflow.py
dataikuscoring/models/model.py
dataikuscoring/models/multiclass.py
dataikuscoring/models/partitioned.py
dataikuscoring/models/regression.py
dataikuscoring/processors/__init__.py
dataikuscoring/processors/binarize.py
dataikuscoring/processors/calibration.py
dataikuscoring/processors/cat_cat_interaction.py
dataikuscoring/processors/categorical_encode.py
dataikuscoring/processors/datetime_cyclical.py
dataikuscoring/processors/derive.py
dataikuscoring/processors/derive_rescale.py
dataikuscoring/processors/drop_rows.py
dataikuscoring/processors/dummify.py
dataikuscoring/processors/flag.py
dataikuscoring/processors/impute.py
dataikuscoring/processors/normalize.py
dataikuscoring/processors/num_cat_interaction.py
dataikuscoring/processors/num_num_interaction.py
dataikuscoring/processors/prepare_input.py
dataikuscoring/processors/preprocessings.py
dataikuscoring/processors/preprocessor.py
dataikuscoring/processors/rescale.py
dataikuscoring/processors/selection.py
dataikuscoring/processors/vectorize_tfidf.py
