Metadata-Version: 2.4
Name: dataiku-scoring
Version: 14.3.3
Summary: Dataiku ML Scoring Python library
Home-page: https://www.dataiku.com
Author: Dataiku
Author-email: support@dataiku.com
License: Apache Software License
Classifier: Development Status :: 5 - Production/Stable
Classifier: Intended Audience :: Developers
Classifier: License :: OSI Approved :: Apache Software License
Classifier: Topic :: Software Development :: Libraries
Classifier: Programming Language :: Python
Classifier: Operating System :: OS Independent
License-File: LICENSE.txt
License-File: NOTICE.txt
Requires-Dist: numpy
Dynamic: author
Dynamic: author-email
Dynamic: classifier
Dynamic: description
Dynamic: home-page
Dynamic: license
Dynamic: license-file
Dynamic: requires-dist
Dynamic: summary
